aiontutil/__init__.py
aiontutil/signal.py
aiontutil-0.1.1.dist-info/METADATA
aiontutil-0.1.1.dist-info/WHEEL
aiontutil-0.1.1.dist-info/RECORD
