Metadata-Version: 2.1
Name: aiontutil
Version: 0.1.1
Summary: aiont util package
Author: mukappalambda
Author-email: maokailan24@gmail.com
Requires-Python: >=3.10,<3.12
Classifier: Programming Language :: Python :: 3
Classifier: Programming Language :: Python :: 3.10
Classifier: Programming Language :: Python :: 3.11
Requires-Dist: numpy (>=1.24.3,<2.0.0)
Requires-Dist: scipy (>=1.10.1,<2.0.0)
